insightlog/__init__.py
insightlog/insight_logger.py
insightlog-1.5.dist-info/licenses/LICENSE
insightlog-1.5.dist-info/METADATA
insightlog-1.5.dist-info/WHEEL
insightlog-1.5.dist-info/top_level.txt
insightlog-1.5.dist-info/RECORD
