Metadata-Version: 2.4
Name: InsightLog
Version: 1.5
Summary: An advanced, feature-rich logging utility with real-time monitoring, performance profiling, anomaly detection, and comprehensive analytics for Python applications.
Home-page: https://github.com/Velyzo/InsightLogger
Download-URL: https://github.com/Velyzo//InsightLog/archive/refs/tags/v1.5.tar.gz
Author: Velyzo
Author-email: help@velyzo.de
License: MIT
Project-URL: Bug Tracker, https://github.com/Velyzo/InsightLog/issues
Project-URL: Documentation, https://github.com/Velyzo/InsightLog/wiki
Project-URL: Source Code, https://github.com/Velyzo/InsightLog
Keywords: logging,log,logger,monitoring,performance,profiling,analytics,dashboard,visualization,anomaly detection,system monitoring,developer tools,debugging,metrics,real-time monitoring,database logging,security logging
Classifier: Development Status :: 5 - Production/Stable
Classifier: Intended Audience :: Developers
Classifier: Topic :: Software Development :: Libraries :: Python Modules
Classifier: Topic :: Software Development :: Libraries
Classifier: License :: OSI Approved :: MIT License
Classifier: Programming Language :: Python :: 3
Classifier: Programming Language :: Python :: 3.9
Classifier: Programming Language :: Python :: 3.10
Classifier: Programming Language :: Python :: 3.11
Classifier: Operating System :: OS Independent
Requires-Python: >=3.9
License-File: LICENSE
Requires-Dist: termcolor>=2.0.0
Requires-Dist: matplotlib>=3.5.0
Requires-Dist: tabulate>=0.9.0
Requires-Dist: psutil>=5.8.0
Requires-Dist: numpy>=1.21.0
Requires-Dist: tqdm>=4.64.0
Dynamic: author
Dynamic: author-email
Dynamic: classifier
Dynamic: description
Dynamic: description-content-type
Dynamic: download-url
Dynamic: home-page
Dynamic: keywords
Dynamic: license
Dynamic: license-file
Dynamic: project-url
Dynamic: requires-dist
Dynamic: requires-python
Dynamic: summary
